malcarve_cbl/__init__.py
malcarve_cbl/find_formats.py
malcarve_cbl/interop.py
malcarve_cbl/keyed_encoding_find.py
malcarve_cbl/lznt1_decompress.py
malcarve_cbl/malcarve.py
malcarve_cbl/timing.py
malcarve_cbl/unkeyed_encoding_find.py
malcarve_cbl/ext/build.sh
malcarve_cbl/ext/ctypes_autogen.py
malcarve_cbl/ext/keyedDecrypt.c
malcarve_cbl/ext/runner.c
malcarve_cbl/ext/build/keyedDecrypt.so
malcarve_cbl-10.0.2.dist-info/METADATA
malcarve_cbl-10.0.2.dist-info/WHEEL
malcarve_cbl-10.0.2.dist-info/top_level.txt
malcarve_cbl-10.0.2.dist-info/RECORD
