Metadata-Version: 2.4
Name: malcarve-cbl
Version: 10.0.2
Summary: Detects and extracts obfuscated, embedded content from files.
Home-page: https://www.asd.gov.au/
Author: Azul
Author-email: azul@asd.gov.au
Classifier: Development Status :: 5 - Production/Stable
Classifier: License :: OSI Approved :: MIT License
Classifier: Programming Language :: Python
Classifier: Programming Language :: Python :: 3
Classifier: Programming Language :: Python :: 3.12
Classifier: Programming Language :: Python :: 3.13
Classifier: Programming Language :: Python :: 3.14
Classifier: Intended Audience :: Developers
Classifier: Topic :: Software Development :: Libraries
Requires-Python: >=3.12
Requires-Dist: olefile
Dynamic: author
Dynamic: author-email
Dynamic: classifier
Dynamic: description
Dynamic: description-content-type
Dynamic: home-page
Dynamic: requires-dist
Dynamic: requires-python
Dynamic: summary
